pofinance/__init__.py
pofinance/api/__init__.py
pofinance/api/shares.py
pofinance/core/__init__.py
pofinance/lib/__init__.py
pofinance-0.0.7.dist-info/LICENSE
pofinance-0.0.7.dist-info/METADATA
pofinance-0.0.7.dist-info/WHEEL
pofinance-0.0.7.dist-info/top_level.txt
pofinance-0.0.7.dist-info/RECORD
