Metadata-Version: 2.1
Name: pofinance
Version: 0.0.7
Summary: pip install pofinance
Home-page: https://www.python-office.com/
Author: CoderWanFeng
Author-email: 1957875073@qq.com
License: MIT
Project-URL: Bug Tracker, https://github.com/CoderWanFeng/pofinance/issues
Project-URL: Documentation, https://github.com/CoderWanFeng/pofinance/blob/master/README.md
Project-URL: Source Code, https://github.com/CoderWanFeng/pofinance
Platform: any
Requires-Python: >=3.5
License-File: LICENSE
